{
	"name": "Elevator",
	"plugin-id": "Sprite",
	"sid": 549710227830281,
	"isGlobal": false,
	"instanceVariables": [],
	"behaviorTypes": [],
	"effectTypes": [],
	"animations": {
		"items": [
			{
				"frames": [
					{
						"width": 74,
						"height": 113,
						"originX": 0.5337837837837838,
						"originY": 0.4690265486725664,
						"originalSource": "",
						"exportFormat": "lossless",
						"exportQuality": 0.8,
						"fileType": "image/png",
						"imageSpriteId": 5497038,
						"collisionPoly": {
							"points": [
								0.013513513513513514,
								0.008849557522123894,
								0.9864864864864865,
								0.008849557522123894,
								0.9864864864864865,
								0.9911504424778761,
								0.013513513513513514,
								0.9911504424778761
							]
						},
						"useCollisionPoly": true,
						"duration": 1,
						"tag": ""
					},
					{
						"width": 74,
						"height": 113,
						"originX": 0.5067567567567568,
						"originY": 0.5,
						"originalSource": "",
						"exportFormat": "lossless",
						"exportQuality": 0.8,
						"fileType": "image/png",
						"imageSpriteId": 3260572,
						"useCollisionPoly": true,
						"duration": 1,
						"tag": ""
					}
				],
				"sid": 181387008933935,
				"name": "Animation 1",
				"isLooping": false,
				"isPingPong": false,
				"repeatCount": 1,
				"repeatTo": 0,
				"speed": 5
			}
		],
		"subfolders": []
	}
}