{
	"name": "TrainClosed",
	"plugin-id": "Sprite",
	"sid": 958308878435687,
	"isGlobal": false,
	"editorNewInstanceIsReplica": true,
	"instanceVariables": [
		{
			"name": "speed",
			"type": "number",
			"desc": "",
			"show": true,
			"sid": 161856867562414
		},
		{
			"name": "Trigger",
			"type": "boolean",
			"desc": "",
			"show": true,
			"sid": 900059783989596
		}
	],
	"behaviorTypes": [
		{
			"behaviorId": "Tween",
			"name": "Твинанимация",
			"sid": 399624577713539
		},
		{
			"behaviorId": "MoveTo",
			"name": "ДвижениеК",
			"sid": 639721881685970
		}
	],
	"effectTypes": [],
	"animations": {
		"items": [
			{
				"frames": [
					{
						"width": 1948,
						"height": 174,
						"originX": 0.5051334702258727,
						"originY": 0.5,
						"originalSource": "",
						"exportFormat": "lossless",
						"exportQuality": 0.8,
						"fileType": "image/png",
						"imageSpriteId": 4300819,
						"collisionPoly": {
							"points": [
								0.0364476386036961,
								0,
								1,
								0,
								1,
								0.8390804597701149,
								0.9142710472279261,
								0.9942528735632183,
								0.048254620123203286,
								1
							]
						},
						"useCollisionPoly": true,
						"duration": 1,
						"tag": ""
					},
					{
						"width": 1948,
						"height": 174,
						"originX": 0.5051334702258727,
						"originY": 0.5,
						"originalSource": "",
						"exportFormat": "lossless",
						"exportQuality": 0.8,
						"fileType": "image/png",
						"imageSpriteId": 6034026,
						"collisionPoly": {
							"points": [
								0.0364476386036961,
								0,
								1,
								0,
								0.9938398357289527,
								0.9482758620689655,
								0.9127310061601642,
								1,
								0.047741273100616016,
								1
							]
						},
						"useCollisionPoly": true,
						"duration": 1,
						"tag": ""
					},
					{
						"width": 1948,
						"height": 174,
						"originX": 0.5051334702258727,
						"originY": 0.5,
						"originalSource": "",
						"exportFormat": "lossless",
						"exportQuality": 0.8,
						"fileType": "image/png",
						"imageSpriteId": 4852501,
						"collisionPoly": {
							"points": [
								0.0364476386036961,
								0,
								1,
								0,
								0.9938398357289527,
								0.9482758620689655,
								0.9127310061601642,
								1,
								0.047741273100616016,
								1
							]
						},
						"useCollisionPoly": true,
						"duration": 1,
						"tag": ""
					},
					{
						"width": 1948,
						"height": 174,
						"originX": 0.5051334702258727,
						"originY": 0.5,
						"originalSource": "",
						"exportFormat": "lossless",
						"exportQuality": 0.8,
						"fileType": "image/png",
						"imageSpriteId": 5044736,
						"collisionPoly": {
							"points": [
								0.0364476386036961,
								0,
								1,
								0,
								0.9938398357289527,
								0.9482758620689655,
								0.9127310061601642,
								1,
								0.047741273100616016,
								1
							]
						},
						"useCollisionPoly": true,
						"duration": 1,
						"tag": ""
					},
					{
						"width": 1948,
						"height": 174,
						"originX": 0.5051334702258727,
						"originY": 0.5,
						"originalSource": "",
						"exportFormat": "lossless",
						"exportQuality": 0.8,
						"fileType": "image/png",
						"imageSpriteId": 2512774,
						"collisionPoly": {
							"points": [
								0.0364476386036961,
								0,
								1,
								0,
								0.9938398357289527,
								0.9482758620689655,
								0.9127310061601642,
								1,
								0.047741273100616016,
								1
							]
						},
						"useCollisionPoly": true,
						"duration": 1,
						"tag": ""
					},
					{
						"width": 1948,
						"height": 174,
						"originX": 0.5051334702258727,
						"originY": 0.5,
						"originalSource": "",
						"exportFormat": "lossless",
						"exportQuality": 0.8,
						"fileType": "image/png",
						"imageSpriteId": 438792,
						"collisionPoly": {
							"points": [
								0.0364476386036961,
								0,
								1,
								0,
								0.9938398357289527,
								0.9482758620689655,
								0.9127310061601642,
								1,
								0.047741273100616016,
								1
							]
						},
						"useCollisionPoly": true,
						"duration": 1,
						"tag": ""
					},
					{
						"width": 1948,
						"height": 174,
						"originX": 0.5051334702258727,
						"originY": 0.5,
						"originalSource": "",
						"exportFormat": "lossless",
						"exportQuality": 0.8,
						"fileType": "image/png",
						"imageSpriteId": 9203751,
						"collisionPoly": {
							"points": [
								0.0364476386036961,
								0,
								1,
								0,
								0.9938398357289527,
								0.9482758620689655,
								0.9127310061601642,
								1,
								0.047741273100616016,
								1
							]
						},
						"useCollisionPoly": true,
						"duration": 1,
						"tag": ""
					},
					{
						"width": 1948,
						"height": 174,
						"originX": 0.5051334702258727,
						"originY": 0.5,
						"originalSource": "",
						"exportFormat": "lossless",
						"exportQuality": 0.8,
						"fileType": "image/png",
						"imageSpriteId": 7343647,
						"collisionPoly": {
							"points": [
								0.0364476386036961,
								0,
								1,
								0,
								0.9938398357289527,
								0.9482758620689655,
								0.9127310061601642,
								1,
								0.047741273100616016,
								1
							]
						},
						"useCollisionPoly": true,
						"duration": 1,
						"tag": ""
					},
					{
						"width": 1948,
						"height": 174,
						"originX": 0.5051334702258727,
						"originY": 0.5,
						"originalSource": "",
						"exportFormat": "lossless",
						"exportQuality": 0.8,
						"fileType": "image/png",
						"imageSpriteId": 5067503,
						"collisionPoly": {
							"points": [
								0.0364476386036961,
								0,
								1,
								0,
								0.9938398357289527,
								0.9482758620689655,
								0.9127310061601642,
								1,
								0.047741273100616016,
								1
							]
						},
						"useCollisionPoly": true,
						"duration": 1,
						"tag": ""
					}
				],
				"sid": 429760429284111,
				"name": "DoorOpen",
				"isLooping": false,
				"isPingPong": false,
				"repeatCount": 1,
				"repeatTo": 0,
				"speed": 10
			},
			{
				"frames": [
					{
						"width": 1948,
						"height": 174,
						"originX": 0.5051334702258727,
						"originY": 0.5,
						"originalSource": "",
						"exportFormat": "lossless",
						"exportQuality": 0.8,
						"fileType": "image/png",
						"imageSpriteId": 238666,
						"collisionPoly": {
							"points": [
								0.0364476386036961,
								0,
								1,
								0,
								0.9938398357289527,
								0.9482758620689655,
								0.9127310061601642,
								1,
								0.047741273100616016,
								1
							]
						},
						"useCollisionPoly": true,
						"duration": 1,
						"tag": ""
					},
					{
						"width": 1948,
						"height": 174,
						"originX": 0.5051334702258727,
						"originY": 0.5,
						"originalSource": "",
						"exportFormat": "lossless",
						"exportQuality": 0.8,
						"fileType": "image/png",
						"imageSpriteId": 9097131,
						"collisionPoly": {
							"points": [
								0.0364476386036961,
								0,
								1,
								0,
								0.9938398357289527,
								0.9482758620689655,
								0.9127310061601642,
								1,
								0.047741273100616016,
								1
							]
						},
						"useCollisionPoly": true,
						"duration": 1,
						"tag": ""
					}
				],
				"sid": 717372379321746,
				"name": "X-ray",
				"isLooping": true,
				"isPingPong": false,
				"repeatCount": 1,
				"repeatTo": 0,
				"speed": 0
			},
			{
				"frames": [
					{
						"width": 1948,
						"height": 174,
						"originX": 0.5051334702258727,
						"originY": 0.5,
						"originalSource": "",
						"exportFormat": "lossless",
						"exportQuality": 0.8,
						"fileType": "image/png",
						"imageSpriteId": 7868211,
						"collisionPoly": {
							"points": [
								0.0364476386036961,
								0,
								1,
								0,
								0.9938398357289527,
								0.9482758620689655,
								0.9127310061601642,
								1,
								0.047741273100616016,
								1
							]
						},
						"useCollisionPoly": true,
						"duration": 1,
						"tag": ""
					},
					{
						"width": 1948,
						"height": 174,
						"originX": 0.5051334702258727,
						"originY": 0.5,
						"originalSource": "",
						"exportFormat": "lossless",
						"exportQuality": 0.8,
						"fileType": "image/png",
						"imageSpriteId": 9339336,
						"collisionPoly": {
							"points": [
								0.0364476386036961,
								0,
								1,
								0,
								0.9938398357289527,
								0.9482758620689655,
								0.9127310061601642,
								1,
								0.047741273100616016,
								1
							]
						},
						"useCollisionPoly": true,
						"duration": 1,
						"tag": ""
					},
					{
						"width": 1948,
						"height": 174,
						"originX": 0.5051334702258727,
						"originY": 0.5,
						"originalSource": "",
						"exportFormat": "lossless",
						"exportQuality": 0.8,
						"fileType": "image/png",
						"imageSpriteId": 8050734,
						"collisionPoly": {
							"points": [
								0.0364476386036961,
								0,
								1,
								0,
								0.9938398357289527,
								0.9482758620689655,
								0.9127310061601642,
								1,
								0.047741273100616016,
								1
							]
						},
						"useCollisionPoly": true,
						"duration": 1,
						"tag": ""
					},
					{
						"width": 1948,
						"height": 174,
						"originX": 0.5051334702258727,
						"originY": 0.5,
						"originalSource": "",
						"exportFormat": "lossless",
						"exportQuality": 0.8,
						"fileType": "image/png",
						"imageSpriteId": 3896401,
						"collisionPoly": {
							"points": [
								0.0364476386036961,
								0,
								1,
								0,
								0.9938398357289527,
								0.9482758620689655,
								0.9127310061601642,
								1,
								0.047741273100616016,
								1
							]
						},
						"useCollisionPoly": true,
						"duration": 1,
						"tag": ""
					},
					{
						"width": 1948,
						"height": 174,
						"originX": 0.5051334702258727,
						"originY": 0.5,
						"originalSource": "",
						"exportFormat": "lossless",
						"exportQuality": 0.8,
						"fileType": "image/png",
						"imageSpriteId": 4296908,
						"collisionPoly": {
							"points": [
								0.0364476386036961,
								0,
								1,
								0,
								0.9938398357289527,
								0.9482758620689655,
								0.9127310061601642,
								1,
								0.047741273100616016,
								1
							]
						},
						"useCollisionPoly": true,
						"duration": 1,
						"tag": ""
					},
					{
						"width": 1948,
						"height": 174,
						"originX": 0.5051334702258727,
						"originY": 0.5,
						"originalSource": "",
						"exportFormat": "lossless",
						"exportQuality": 0.8,
						"fileType": "image/png",
						"imageSpriteId": 5508214,
						"collisionPoly": {
							"points": [
								0.0364476386036961,
								0,
								1,
								0,
								0.9938398357289527,
								0.9482758620689655,
								0.9127310061601642,
								1,
								0.047741273100616016,
								1
							]
						},
						"useCollisionPoly": true,
						"duration": 1,
						"tag": ""
					},
					{
						"width": 1948,
						"height": 174,
						"originX": 0.5051334702258727,
						"originY": 0.5,
						"originalSource": "",
						"exportFormat": "lossless",
						"exportQuality": 0.8,
						"fileType": "image/png",
						"imageSpriteId": 1315176,
						"collisionPoly": {
							"points": [
								0.0364476386036961,
								0,
								1,
								0,
								0.9938398357289527,
								0.9482758620689655,
								0.9127310061601642,
								1,
								0.047741273100616016,
								1
							]
						},
						"useCollisionPoly": true,
						"duration": 1,
						"tag": ""
					},
					{
						"width": 1948,
						"height": 174,
						"originX": 0.5051334702258727,
						"originY": 0.5,
						"originalSource": "",
						"exportFormat": "lossless",
						"exportQuality": 0.8,
						"fileType": "image/png",
						"imageSpriteId": 8476252,
						"collisionPoly": {
							"points": [
								0.0364476386036961,
								0,
								1,
								0,
								0.9938398357289527,
								0.9482758620689655,
								0.9127310061601642,
								1,
								0.047741273100616016,
								1
							]
						},
						"useCollisionPoly": true,
						"duration": 1,
						"tag": ""
					},
					{
						"width": 1948,
						"height": 174,
						"originX": 0.5051334702258727,
						"originY": 0.5,
						"originalSource": "",
						"exportFormat": "lossless",
						"exportQuality": 0.8,
						"fileType": "image/png",
						"imageSpriteId": 3199366,
						"collisionPoly": {
							"points": [
								0.0364476386036961,
								0,
								1,
								0,
								1,
								0.8390804597701149,
								0.9142710472279261,
								0.9942528735632183,
								0.048254620123203286,
								1
							]
						},
						"useCollisionPoly": true,
						"duration": 1,
						"tag": ""
					}
				],
				"sid": 602748642782741,
				"name": "DoorClosed",
				"isLooping": false,
				"isPingPong": false,
				"repeatCount": 1,
				"repeatTo": 0,
				"speed": 10
			},
			{
				"frames": [
					{
						"width": 1948,
						"height": 174,
						"originX": 0.5051334702258727,
						"originY": 0.5,
						"originalSource": "",
						"exportFormat": "lossless",
						"exportQuality": 0.8,
						"fileType": "image/png",
						"imageSpriteId": 6523138,
						"collisionPoly": {
							"points": [
								0.0364476386036961,
								0,
								1,
								0,
								1,
								0.8390804597701149,
								0.9142710472279261,
								0.9942528735632183,
								0.048254620123203286,
								1
							]
						},
						"useCollisionPoly": true,
						"duration": 1,
						"tag": ""
					}
				],
				"sid": 175506455173544,
				"name": "Closed",
				"isLooping": false,
				"isPingPong": false,
				"repeatCount": 1,
				"repeatTo": 0,
				"speed": 5
			},
			{
				"frames": [
					{
						"width": 1948,
						"height": 174,
						"originX": 0.5051334702258727,
						"originY": 0.5,
						"originalSource": "",
						"exportFormat": "lossless",
						"exportQuality": 0.8,
						"fileType": "image/png",
						"imageSpriteId": 9804724,
						"collisionPoly": {
							"points": [
								0.0364476386036961,
								0,
								1,
								0,
								0.9938398357289527,
								0.9482758620689655,
								0.9127310061601642,
								1,
								0.047741273100616016,
								1
							]
						},
						"useCollisionPoly": true,
						"duration": 1,
						"tag": ""
					},
					{
						"width": 1948,
						"height": 174,
						"originX": 0.5051334702258727,
						"originY": 0.5,
						"originalSource": "",
						"exportFormat": "lossless",
						"exportQuality": 0.8,
						"fileType": "image/png",
						"imageSpriteId": 1268237,
						"collisionPoly": {
							"points": [
								0.0364476386036961,
								0,
								1,
								0,
								0.9938398357289527,
								0.9482758620689655,
								0.9127310061601642,
								1,
								0.047741273100616016,
								1
							]
						},
						"useCollisionPoly": true,
						"duration": 1,
						"tag": ""
					},
					{
						"width": 1948,
						"height": 174,
						"originX": 0.5051334702258727,
						"originY": 0.5,
						"originalSource": "",
						"exportFormat": "lossless",
						"exportQuality": 0.8,
						"fileType": "image/png",
						"imageSpriteId": 190561,
						"collisionPoly": {
							"points": [
								0.0364476386036961,
								0,
								1,
								0,
								0.9938398357289527,
								0.9482758620689655,
								0.9127310061601642,
								1,
								0.047741273100616016,
								1
							]
						},
						"useCollisionPoly": true,
						"duration": 1,
						"tag": ""
					},
					{
						"width": 1948,
						"height": 174,
						"originX": 0.5051334702258727,
						"originY": 0.5,
						"originalSource": "",
						"exportFormat": "lossless",
						"exportQuality": 0.8,
						"fileType": "image/png",
						"imageSpriteId": 2815522,
						"collisionPoly": {
							"points": [
								0.0364476386036961,
								0,
								1,
								0,
								0.9938398357289527,
								0.9482758620689655,
								0.9127310061601642,
								1,
								0.047741273100616016,
								1
							]
						},
						"useCollisionPoly": true,
						"duration": 1,
						"tag": ""
					},
					{
						"width": 1948,
						"height": 174,
						"originX": 0.5051334702258727,
						"originY": 0.5,
						"originalSource": "",
						"exportFormat": "lossless",
						"exportQuality": 0.8,
						"fileType": "image/png",
						"imageSpriteId": 2950899,
						"collisionPoly": {
							"points": [
								0.0364476386036961,
								0,
								1,
								0,
								0.9938398357289527,
								0.9482758620689655,
								0.9127310061601642,
								1,
								0.047741273100616016,
								1
							]
						},
						"useCollisionPoly": true,
						"duration": 1,
						"tag": ""
					},
					{
						"width": 1948,
						"height": 174,
						"originX": 0.5051334702258727,
						"originY": 0.5,
						"originalSource": "",
						"exportFormat": "lossless",
						"exportQuality": 0.8,
						"fileType": "image/png",
						"imageSpriteId": 1881990,
						"collisionPoly": {
							"points": [
								0.0364476386036961,
								0,
								1,
								0,
								0.9938398357289527,
								0.9482758620689655,
								0.9127310061601642,
								1,
								0.047741273100616016,
								1
							]
						},
						"useCollisionPoly": true,
						"duration": 1,
						"tag": ""
					},
					{
						"width": 1948,
						"height": 174,
						"originX": 0.5051334702258727,
						"originY": 0.5,
						"originalSource": "",
						"exportFormat": "lossless",
						"exportQuality": 0.8,
						"fileType": "image/png",
						"imageSpriteId": 2721251,
						"collisionPoly": {
							"points": [
								0.0364476386036961,
								0,
								1,
								0,
								0.9938398357289527,
								0.9482758620689655,
								0.9127310061601642,
								1,
								0.047741273100616016,
								1
							]
						},
						"useCollisionPoly": true,
						"duration": 1,
						"tag": ""
					},
					{
						"width": 1948,
						"height": 174,
						"originX": 0.5051334702258727,
						"originY": 0.5,
						"originalSource": "",
						"exportFormat": "lossless",
						"exportQuality": 0.8,
						"fileType": "image/png",
						"imageSpriteId": 1563362,
						"collisionPoly": {
							"points": [
								0.0364476386036961,
								0,
								1,
								0,
								0.9938398357289527,
								0.9482758620689655,
								0.9127310061601642,
								1,
								0.047741273100616016,
								1
							]
						},
						"useCollisionPoly": true,
						"duration": 1,
						"tag": ""
					},
					{
						"width": 1948,
						"height": 174,
						"originX": 0.5051334702258727,
						"originY": 0.5,
						"originalSource": "",
						"exportFormat": "lossless",
						"exportQuality": 0.8,
						"fileType": "image/png",
						"imageSpriteId": 3054391,
						"collisionPoly": {
							"points": [
								0.0364476386036961,
								0,
								1,
								0,
								0.9938398357289527,
								0.9482758620689655,
								0.9127310061601642,
								1,
								0.047741273100616016,
								1
							]
						},
						"useCollisionPoly": true,
						"duration": 1,
						"tag": ""
					}
				],
				"sid": 438248149896622,
				"name": "X-ray2",
				"isLooping": false,
				"isPingPong": false,
				"repeatCount": 1,
				"repeatTo": 0,
				"speed": 0
			},
			{
				"frames": [
					{
						"width": 3500,
						"height": 174,
						"originX": 0.5,
						"originY": 0.5,
						"originalSource": "",
						"exportFormat": "lossless",
						"exportQuality": 0.8,
						"fileType": "image/png",
						"imageSpriteId": 1954060,
						"collisionPoly": {
							"points": [
								0.242,
								0,
								0.7782857142857142,
								0,
								0.7748571428571429,
								0.9482758620689655,
								0.7297142857142858,
								1,
								0.24828571428571428,
								1
							]
						},
						"useCollisionPoly": true,
						"imagePoints": [
							{
								"name": "Точка спрайта 1",
								"x": 0.8905714285714286,
								"y": 0.9655172413793104
							},
							{
								"name": "Точка спрайта 2",
								"x": 0.984,
								"y": 0.9597701149425287
							},
							{
								"name": "Точка спрайта 3",
								"x": 0.7914285714285715,
								"y": 0.9655172413793104
							},
							{
								"name": "Точка спрайта 4",
								"x": 0.698,
								"y": 0.9655172413793104
							},
							{
								"name": "Точка спрайта 5",
								"x": 0.6042857142857143,
								"y": 0.9655172413793104
							},
							{
								"name": "Точка спрайта 6",
								"x": 0.542,
								"y": 0.9655172413793104
							},
							{
								"name": "Точка спрайта 7",
								"x": 0.44885714285714284,
								"y": 0.9540229885057471
							},
							{
								"name": "Точка спрайта 8",
								"x": 0.3494285714285714,
								"y": 0.9540229885057471
							},
							{
								"name": "Точка спрайта 9",
								"x": 0.2562857142857143,
								"y": 0.9655172413793104
							},
							{
								"name": "Точка спрайта 10",
								"x": 0.16228571428571428,
								"y": 0.9597701149425287
							},
							{
								"name": "Точка спрайта 11",
								"x": 0.9302857142857143,
								"y": 0.08045977011494253
							},
							{
								"name": "Точка спрайта 12",
								"x": 0.9562857142857143,
								"y": 0.05747126436781609
							}
						],
						"duration": 1,
						"tag": ""
					},
					{
						"width": 3500,
						"height": 174,
						"originX": 0.5,
						"originY": 0.5,
						"originalSource": "",
						"exportFormat": "lossless",
						"exportQuality": 0.8,
						"fileType": "image/png",
						"imageSpriteId": 3566689,
						"collisionPoly": {
							"points": [
								0.052,
								0,
								1,
								0,
								0.996,
								0.9482758620689655,
								0.982,
								1,
								0.05857142857142857,
								1
							]
						},
						"useCollisionPoly": true,
						"imagePoints": [
							{
								"name": "Точка спрайта 1",
								"x": 0.8905714285714286,
								"y": 0.9655172413793104
							},
							{
								"name": "Точка спрайта 2",
								"x": 0.984,
								"y": 0.9597701149425287
							},
							{
								"name": "Точка спрайта 3",
								"x": 0.7914285714285715,
								"y": 0.9655172413793104
							},
							{
								"name": "Точка спрайта 4",
								"x": 0.698,
								"y": 0.9655172413793104
							},
							{
								"name": "Точка спрайта 5",
								"x": 0.6042857142857143,
								"y": 0.9655172413793104
							},
							{
								"name": "Точка спрайта 6",
								"x": 0.542,
								"y": 0.9655172413793104
							},
							{
								"name": "Точка спрайта 7",
								"x": 0.44885714285714284,
								"y": 0.9540229885057471
							},
							{
								"name": "Точка спрайта 8",
								"x": 0.3494285714285714,
								"y": 0.9540229885057471
							},
							{
								"name": "Точка спрайта 9",
								"x": 0.2562857142857143,
								"y": 0.9655172413793104
							},
							{
								"name": "Точка спрайта 10",
								"x": 0.16228571428571428,
								"y": 0.9597701149425287
							},
							{
								"name": "Точка спрайта 11",
								"x": 0.06885714285714285,
								"y": 0.9712643678160919
							}
						],
						"duration": 1,
						"tag": ""
					},
					{
						"width": 3500,
						"height": 174,
						"originX": 0.5,
						"originY": 0.5,
						"originalSource": "",
						"exportFormat": "lossless",
						"exportQuality": 0.8,
						"fileType": "image/png",
						"imageSpriteId": 4092369,
						"collisionPoly": {
							"points": [
								0.052,
								0,
								1,
								0,
								0.996,
								0.9482758620689655,
								0.982,
								1,
								0.05857142857142857,
								1
							]
						},
						"useCollisionPoly": true,
						"imagePoints": [
							{
								"name": "Точка спрайта 1",
								"x": 0.8905714285714286,
								"y": 0.9655172413793104
							},
							{
								"name": "Точка спрайта 2",
								"x": 0.984,
								"y": 0.9597701149425287
							},
							{
								"name": "Точка спрайта 3",
								"x": 0.7914285714285715,
								"y": 0.9655172413793104
							},
							{
								"name": "Точка спрайта 4",
								"x": 0.698,
								"y": 0.9655172413793104
							},
							{
								"name": "Точка спрайта 5",
								"x": 0.6042857142857143,
								"y": 0.9655172413793104
							},
							{
								"name": "Точка спрайта 6",
								"x": 0.542,
								"y": 0.9655172413793104
							},
							{
								"name": "Точка спрайта 7",
								"x": 0.44885714285714284,
								"y": 0.9540229885057471
							},
							{
								"name": "Точка спрайта 8",
								"x": 0.3494285714285714,
								"y": 0.9540229885057471
							},
							{
								"name": "Точка спрайта 9",
								"x": 0.2562857142857143,
								"y": 0.9655172413793104
							},
							{
								"name": "Точка спрайта 10",
								"x": 0.16228571428571428,
								"y": 0.9597701149425287
							},
							{
								"name": "Точка спрайта 11",
								"x": 0.06885714285714285,
								"y": 0.9712643678160919
							}
						],
						"duration": 1,
						"tag": ""
					},
					{
						"width": 3500,
						"height": 174,
						"originX": 0.5,
						"originY": 0.5,
						"originalSource": "",
						"exportFormat": "lossless",
						"exportQuality": 0.8,
						"fileType": "image/png",
						"imageSpriteId": 761093,
						"collisionPoly": {
							"points": [
								0.052,
								0,
								1,
								0,
								0.996,
								0.9482758620689655,
								0.982,
								1,
								0.05857142857142857,
								1
							]
						},
						"useCollisionPoly": true,
						"imagePoints": [
							{
								"name": "Точка спрайта 1",
								"x": 0.8905714285714286,
								"y": 0.9655172413793104
							},
							{
								"name": "Точка спрайта 2",
								"x": 0.984,
								"y": 0.9597701149425287
							},
							{
								"name": "Точка спрайта 3",
								"x": 0.7914285714285715,
								"y": 0.9655172413793104
							},
							{
								"name": "Точка спрайта 4",
								"x": 0.698,
								"y": 0.9655172413793104
							},
							{
								"name": "Точка спрайта 5",
								"x": 0.6042857142857143,
								"y": 0.9655172413793104
							},
							{
								"name": "Точка спрайта 6",
								"x": 0.542,
								"y": 0.9655172413793104
							},
							{
								"name": "Точка спрайта 7",
								"x": 0.44885714285714284,
								"y": 0.9540229885057471
							},
							{
								"name": "Точка спрайта 8",
								"x": 0.3494285714285714,
								"y": 0.9540229885057471
							},
							{
								"name": "Точка спрайта 9",
								"x": 0.2562857142857143,
								"y": 0.9655172413793104
							},
							{
								"name": "Точка спрайта 10",
								"x": 0.16228571428571428,
								"y": 0.9597701149425287
							},
							{
								"name": "Точка спрайта 11",
								"x": 0.06885714285714285,
								"y": 0.9712643678160919
							}
						],
						"duration": 1,
						"tag": ""
					}
				],
				"sid": 757597314796093,
				"name": "Train",
				"isLooping": true,
				"isPingPong": false,
				"repeatCount": 1,
				"repeatTo": 0,
				"speed": 10
			},
			{
				"frames": [
					{
						"width": 1736,
						"height": 132,
						"originX": 0.5,
						"originY": 0.5,
						"originalSource": "",
						"exportFormat": "lossless",
						"exportQuality": 0.8,
						"fileType": "image/png",
						"imageSpriteId": 2170933,
						"useCollisionPoly": true,
						"duration": 1,
						"tag": ""
					}
				],
				"sid": 129396529217590,
				"name": "Анимация 1",
				"isLooping": false,
				"isPingPong": false,
				"repeatCount": 1,
				"repeatTo": 0,
				"speed": 5
			},
			{
				"frames": [
					{
						"width": 153,
						"height": 14,
						"originX": 0.5098039215686274,
						"originY": 3.7142857142857144,
						"originalSource": "",
						"exportFormat": "lossless",
						"exportQuality": 0.8,
						"fileType": "image/png",
						"imageSpriteId": 5833790,
						"useCollisionPoly": true,
						"duration": 1,
						"tag": ""
					}
				],
				"sid": 302983527463818,
				"name": "Анимация 2",
				"isLooping": false,
				"isPingPong": false,
				"repeatCount": 1,
				"repeatTo": 0,
				"speed": 5
			}
		],
		"subfolders": []
	}
}